parsematic/__init__.py
parsematic/__main__.py
parsematic-1.0.0.dist-info/LICENSE
parsematic-1.0.0.dist-info/METADATA
parsematic-1.0.0.dist-info/WHEEL
parsematic-1.0.0.dist-info/RECORD
